{
  "date": "2025-12-22",
  "snapshot_generated_at": "2025-12-25T20:45:21.377447",
  "data": {
    "market_data": {
      "XAUUSD_OPEN": 4338.9,
      "XAUUSD_HIGH": 4448.94,
      "XAUUSD_LOW": 4336.64,
      "XAUUSD_CLOSE": 4442.81,
      "USA500.IDX_OPEN": 6852.64,
      "USA500.IDX_HIGH": 6882.45,
      "USA500.IDX_LOW": 6846.35,
      "USA500.IDX_CLOSE": 6877.65,
      "VOL.IDX_OPEN": 17.13,
      "VOL.IDX_HIGH": 17.18,
      "VOL.IDX_LOW": 16.72,
      "VOL.IDX_CLOSE": 16.77,
      "DOLLAR.IDX_OPEN": 98.27,
      "DOLLAR.IDX_HIGH": 98.3,
      "DOLLAR.IDX_LOW": 97.84,
      "DOLLAR.IDX_CLOSE": 97.92
    },
    "technicals": {
      "XAUUSD_RSI": 78.58,
      "XAUUSD_RSI_STATUS": "Overbought",
      "XAUUSD_EMA50": 4127.58,
      "XAUUSD_EMA200": 3642.93,
      "XAUUSD_EMA_TREND": "Bullish",
      "XAUUSD_MACD": 72.65,
      "XAUUSD_MACD_SIGNAL": 60.42,
      "XAUUSD_MACD_HIST": 12.23,
      "XAUUSD_STOCH_K": 97.8,
      "XAUUSD_STOCH_D": 86.7,
      "XAUUSD_STOCH_STATUS": "Exhaustion Near Highs",
      "USA500.IDX_RSI": 57.44,
      "USA500.IDX_RSI_STATUS": "Neutral",
      "USA500.IDX_EMA50": 6761.91,
      "USA500.IDX_EMA200": 6425.07,
      "USA500.IDX_EMA_TREND": "Bullish",
      "USA500.IDX_MACD": 17.17,
      "USA500.IDX_MACD_SIGNAL": 20.52,
      "USA500.IDX_MACD_HIST": -3.35,
      "USA500.IDX_STOCH_K": 82.61,
      "USA500.IDX_STOCH_D": 56.15,
      "USA500.IDX_STOCH_STATUS": "Neutral",
      "VOL.IDX_RSI": 42.24,
      "VOL.IDX_RSI_STATUS": "Neutral",
      "VOL.IDX_EMA50": 18.32,
      "VOL.IDX_EMA200": 18.6,
      "VOL.IDX_EMA_TREND": "Bearish",
      "VOL.IDX_MACD": -0.47,
      "VOL.IDX_MACD_SIGNAL": -0.5,
      "VOL.IDX_MACD_HIST": 0.03,
      "VOL.IDX_STOCH_K": 30.41,
      "VOL.IDX_STOCH_D": 52.03,
      "VOL.IDX_STOCH_STATUS": "Neutral",
      "DOLLAR.IDX_RSI": 35.77,
      "DOLLAR.IDX_RSI_STATUS": "Neutral",
      "DOLLAR.IDX_EMA50": 98.75,
      "DOLLAR.IDX_EMA200": 99.8,
      "DOLLAR.IDX_EMA_TREND": "Bearish",
      "DOLLAR.IDX_MACD": -0.34,
      "DOLLAR.IDX_MACD_SIGNAL": -0.25,
      "DOLLAR.IDX_MACD_HIST": -0.09,
      "DOLLAR.IDX_STOCH_K": 23.84,
      "DOLLAR.IDX_STOCH_D": 32.23,
      "DOLLAR.IDX_STOCH_STATUS": "Neutral"
    },
    "fundamentals": {
      "TREASURY_10Y": 4.17,
      "HY_CREDIT_SPREAD": 2.88,
      "GLD_CLOSE": 408.23,
      "GLD_VOLUME": 14202100,
      "IAU_CLOSE": 83.59,
      "IAU_VOLUME": 6309800,
      "REAL_RATE": 1.17
    },
    "economic_events": [
      {
        "time": "19:00",
        "currency": "USD",
        "event": "2-Year Note Auction",
        "actual": "3.499%",
        "forecast": "",
        "previous": "3.489%"
      }
    ],
    "news": [
      {
        "category": "market",
        "title": "QQQ to Become an Open-End Fund",
        "ticker": "QQQ"
      },
      {
        "category": "market",
        "title": "Here Are the Top ETFs Holding Oracle after Its Nosedive",
        "ticker": "SPY"
      },
      {
        "category": "market",
        "title": "The Safest Way to Bet on the Santa Claus Rally",
        "ticker": "SPY"
      },
      {
        "category": "market",
        "title": "Silent Time Bomb Threatens 6 AI S&P 500 Stocks Loading Up With Debt",
        "ticker": "SPY"
      },
      {
        "category": "market",
        "title": "Will Santa Claus Rally Set In for 2025? 4 Best ETF Areas to Explore",
        "ticker": "SPY"
      },
      {
        "category": "gold",
        "title": "How to Invest in Gold",
        "ticker": "GLD"
      },
      {
        "category": "market",
        "title": "Stock Market Today: Dow Rises As Nvidia Climbs; Rocket Name Soars (Live Coverage)",
        "ticker": "SPY"
      },
      {
        "category": "market",
        "title": "MarketBeats Top 5 Rated Small-Cap Stocks",
        "ticker": "IWM"
      },
      {
        "category": "gold",
        "title": "The Biggest ETF Stories of 2025 and the 2026 Outlook",
        "ticker": "GLD"
      },
      {
        "category": "market",
        "title": "Stock Indexes Close Higher on Strength in Tech Stocks",
        "ticker": "SPY"
      }
    ],
    "reddit": [
      {
        "title": "This is what oligarchy looks like.",
        "source": "r/economy"
      },
      {
        "title": "Electronic Arts Shareholders Approve $55 Billion Sale to Saudis",
        "source": "r/wallstreetbets"
      },
      {
        "title": "Larry Ellison backstops $40.4B Paramount bid for Warner Bros. PSKY +4.3%, WBD +3.5%",
        "source": "r/wallstreetbets"
      },
      {
        "title": "Ready for the comeback 🥷",
        "source": "r/wallstreetbets"
      },
      {
        "title": "What Are Your Moves Tomorrow, December 23, 2025",
        "source": "r/wallstreetbets"
      },
      {
        "title": "All time gains in Robinhood",
        "source": "r/wallstreetbets"
      },
      {
        "title": "The Economy Survived 2025, But Many Americans Are Reeling - A feared recession didn’t materialize, but unemployment rose, wage growth slowed and affordability challenges are mounting",
        "source": "r/economics"
      },
      {
        "title": "An American Dream at risk: What happens to a small Nebraska town when 3,200 workers lose their jobs",
        "source": "r/economics"
      },
      {
        "title": "A Pure Gambling Play: LUNR (800% gain so far)",
        "source": "r/wallstreetbets"
      },
      {
        "title": "Is the current market drunk?",
        "source": "r/investing"
      },
      {
        "title": "Sold some TSLA in Nov'25 to buy RKLB - 2nd best invest decision made",
        "source": "r/wallstreetbets"
      },
      {
        "title": "Pre holiday gains. +5.3k",
        "source": "r/SPY"
      },
      {
        "title": "Alphabet to acquire data center and energy infrastructure company Intersect",
        "source": "r/wallstreetbets"
      },
      {
        "title": "Ex-Saudi intel chief to ToI: Riyadh will consider normalization when Israel acts normally",
        "source": "r/geopolitics"
      },
      {
        "title": "Trump still wants to take over Greenland - and he won't stop there",
        "source": "r/geopolitics"
      },
      {
        "title": "Larry Ellison offers $40.4 billion guarantee for Warner Bros",
        "source": "r/StockMarket"
      },
      {
        "title": "How can Rocket Lab be a good long term investment",
        "source": "r/stocks"
      },
      {
        "title": "Fed Risks Recession Without More Interest Rate Cuts, Miran Says",
        "source": "r/economics"
      },
      {
        "title": "US halts five offshore wind projects citing national security concerns",
        "source": "r/stocks"
      },
      {
        "title": "Why gold and tech stocks are rallying at the same time",
        "source": "r/StockMarket"
      },
      {
        "title": "I'm tired of anonymous reddit investing advice from people who won't show positions",
        "source": "r/stocks"
      },
      {
        "title": "WSB 2025: Year in Review (with sound) 🥂",
        "source": "r/wallstreetbets"
      },
      {
        "title": "China hits EU dairy products with provisional duties up to 42.7%",
        "source": "r/economics"
      },
      {
        "title": "Nvidia plans 40,000–80,000 H200 AI chips to China by mid-February pending approval",
        "source": "r/StockMarket"
      },
      {
        "title": "Daily Discussion Thread for December 22, 2025",
        "source": "r/wallstreetbets"
      },
      {
        "title": "I have some photos from the 1980s and 1990s in Chengdu, China. I'd like to share them here and also tell some of my own little stories. Would you like to see them, or is it appropriate to post them here?",
        "source": "r/China"
      },
      {
        "title": "Gold and Silver Hit Record Highs Amid Escalation Risks Around Venezuela and Expectations of U.S. Rate Cuts. Investors Turn to Precious Metals as a Hedge Against Geopolitical and Currency Risks",
        "source": "r/economics"
      },
      {
        "title": "If SpaceX goes public in 2026, what happens to Starlink?",
        "source": "r/investing"
      },
      {
        "title": "Thanks E-Toro I guess",
        "source": "r/wallstreetbets"
      },
      {
        "title": "US, Venezuela, Cuba and Russia: Russia's lack of force, or a deal?",
        "source": "r/geopolitics"
      },
      {
        "title": "Doctor says I should take profits, I say rockets go up (RKLB)",
        "source": "r/wallstreetbets"
      },
      {
        "title": "Algerian asking for advice about Chinese citizenship and life",
        "source": "r/China"
      },
      {
        "title": "Global trends favor phone-free schools as Japan still debating action",
        "source": "r/japan"
      },
      {
        "title": "Voters in Hamburg have rejected universal basic income. Many economists would agree with them",
        "source": "r/economics"
      },
      {
        "title": "It’s a beautiful time to believe in space (RKLB)",
        "source": "r/wallstreetbets"
      },
      {
        "title": "Key data for the coming week",
        "source": "r/wallstreetbets"
      },
      {
        "title": "Waymo suspends service in San Francisco after driverless cars cause traffic jams during blackout",
        "source": "r/stocks"
      },
      {
        "title": "Dark Horse Picks for 2026",
        "source": "r/wallstreetbets"
      },
      {
        "title": "UK stocks outperformed Wall Street this year — and investors see more upside ahead in 2026",
        "source": "r/StockMarket"
      }
    ]
  }
}